my_pickledb/__init__.py
my_pickledb/__main__.py
my_pickledb/pickledb.py
my_pickledb/utils.py
oh_my_pickledb-0.4.2.dist-info/LICENSE
oh_my_pickledb-0.4.2.dist-info/METADATA
oh_my_pickledb-0.4.2.dist-info/WHEEL
oh_my_pickledb-0.4.2.dist-info/top_level.txt
oh_my_pickledb-0.4.2.dist-info/RECORD
