Metadata-Version: 2.1
Name: oh-my-pickledb
Version: 0.4.2
Summary: Oh-My-PickleDB is an open source key-value store using Python's json module
Home-page: https://tory1103.github.io/oh-my-pickledb/
Author: Adrián Toral
Author-email: adriantoral@sertor.es
License: UNKNOWN
Project-URL: Website, https://github.com/tory1103/oh-my-pickledb
Project-URL: Documentation, https://tory1103.github.io/oh-my-pickledb/docs.html
Project-URL: Issues, https://github.com/tory1103/oh-my-pickledb/issues
Keywords: python,json,database,key-value,python3,datastore,fernet,encryption-decryption,fernet-encryption
Platform: UNKNOWN
Classifier: Programming Language :: Python :: 3
Classifier: License :: OSI Approved :: GNU General Public License v3 (GPLv3)
Classifier: Operating System :: OS Independent
Classifier: Topic :: Database
Requires-Python: >=3.6
License-File: LICENSE
Requires-Dist: cryptography (~=3.4.8)
Requires-Dist: fire (~=0.4.0)
Requires-Dist: pysem-converters (==0.1)
